README.rst
setup.py
urlshots.py
urlshots_api.egg-info/PKG-INFO
urlshots_api.egg-info/SOURCES.txt
urlshots_api.egg-info/dependency_links.txt
urlshots_api.egg-info/requires.txt
urlshots_api.egg-info/top_level.txt