Metadata-Version: 1.0
Name: urlshots-api
Version: 0.2.0-dev
Summary: UrlShots API Python Client
Home-page: http://bitbucket.org/urlshots/urlshots-api
Author: Jacob Alheid
Author-email: jake@about.me
License: UNKNOWN
Platform: UNKNOWN
